Workbook

Sheet Executive Summary
A1: Executive Summary
A2: ="Active scenario: "&Assumptions!$B$4&" | Figures below reflect the currently selected scenario, except the scenario comparison table." -> Active scenario: Base | Figures below reflect the currently selected scenario, except the scenario comparison table.
A4: Headline KPIs (Year 1 -> Year 6, current scenario)
B5: 2026A | C5: 2031E | D5: CAGR / Change
A6: Revenue | B6: ='Income Statement'!B4 -> 100000 | C6: ='Income Statement'!G4 -> 146932.81 | D6: =(C6/B6)^(1/5)-1 -> 0.08
A7: Net Income | B7: ='Income Statement'!B14 -> 10560 | C7: ='Income Statement'!G14 -> 16191.937 | D7: =(C7/B7)^(1/5)-1 -> 0.089248516
A8: EBITDA Margin | B8: ='Income Statement'!B8/'Income Statement'!B4 -> 0.2 | C8: ='Income Statement'!G8/'Income Statement'!G4 -> 0.2 | D8: =C8-B8 -> 0
A9: Net Margin | B9: ='Income Statement'!B14/'Income Statement'!B4 -> 0.1056 | C9: ='Income Statement'!G14/'Income Statement'!G4 -> 0.1101996 | D9: =C9-B9 -> 0.004599602
A10: Ending Cash | B10: ='Balance Sheet'!B4 -> 15000 | C10: ='Balance Sheet'!G4 -> 71267.553 | D10: =(C10/B10)^(1/5)-1 -> 0.36571512
A11: CAGR = Compound Annual Growth Rate (average yearly growth over the 5 forecast years).
A13: Revenue & Net Income Trend (current scenario)
B14: 2026A | C14: 2027E | D14: 2028E | E14: 2029E | F14: 2030E | G14: 2031E
A15: Revenue | B15: ='Income Statement'!B4 -> 100000 | C15: ='Income Statement'!C4 -> 108000 | D15: ='Income Statement'!D4 -> 116640 | E15: ='Income Statement'!E4 -> 125971.2 | F15: ='Income Statement'!F4 -> 136048.9 | G15: ='Income Statement'!G4 -> 146932.81
A16: Net Income | B16: ='Income Statement'!B14 -> 10560 | C16: ='Income Statement'!C14 -> 11520 | D16: ='Income Statement'!D14 -> 12556.8 | E16: ='Income Statement'!E14 -> 13676.544 | F16: ='Income Statement'!F14 -> 14885.868 | G16: ='Income Statement'!G14 -> 16191.937
A34: Scenario Comparison — 2031E (Year 6)
B35: Base | C35: Upside | D35: Downside
A36: Revenue | B36: =Assumptions!$B$23*(1+Assumptions!$C$7)^5 -> 146932.81 | C36: =Assumptions!$B$23*(1+Assumptions!$D$7)^5 -> 201135.72 | D36: =Assumptions!$B$23*(1+Assumptions!$E$7)^5 -> 110408.08
A37: Net Income | B37: =((((((((((Assumptions!$B$23*(1+Assumptions!$C$7)^5)-((Assumptions!$B$23*(1+Assumptions!$C$7)^5)*Assumptions!$C$8)))-((Assumptions!$B$23*(1+Assumptions!$C$7)^5)*Assumptions!$C$9)))-((Assumptions!$B$23*(1+Assumptions!$C$7)^5)*Assumptions!$C$10)))-(Assumptions!$B$26*Assumptions!$C$12)))-(((((((((((Assumptions!$B$23*(1+Assumptions!$C$7)^5)-((Assumptions!$B$23*(1+Assumptions!$C$7)^5)*Assumptions!$C$8)))-((Assumptions!$B$23*(1+Assumptions!$C$7)^5)*Assumptions!$C$9)))-((Assumptions!$B$23*(1+Assumptions!$C$7)^5)*Assumptions!$C$10)))-(Assumptions!$B$26*Assumptions!$C$12)))*Assumptions!$C$11))) -> 16191.937 | C37: =((((((((((Assumptions!$B$23*(1+Assumptions!$D$7)^5)-((Assumptions!$B$23*(1+Assumptions!$D$7)^5)*Assumptions!$D$8)))-((Assumptions!$B$23*(1+Assumptions!$D$7)^5)*Assumptions!$D$9)))-((Assumptions!$B$23*(1+Assumptions!$D$7)^5)*Assumptions!$D$10)))-(Assumptions!$B$26*Assumptions!$D$12)))-(((((((((((Assumptions!$B$23*(1+Assumptions!$D$7)^5)-((Assumptions!$B$23*(1+Assumptions!$D$7)^5)*Assumptions!$D$8)))-((Assumptions!$B$23*(1+Assumptions!$D$7)^5)*Assumptions!$D$9)))-((Assumptions!$B$23*(1+Assumptions!$D$7)^5)*Assumptions!$D$10)))-(Assumptions!$B$26*Assumptions!$D$12)))*Assumptions!$D$11))) -> 29132.629 | D37: =((((((((((Assumptions!$B$23*(1+Assumptions!$E$7)^5)-((Assumptions!$B$23*(1+Assumptions!$E$7)^5)*Assumptions!$E$8)))-((Assumptions!$B$23*(1+Assumptions!$E$7)^5)*Assumptions!$E$9)))-((Assumptions!$B$23*(1+Assumptions!$E$7)^5)*Assumptions!$E$10)))-(Assumptions!$B$26*Assumptions!$E$12)))-(((((((((((Assumptions!$B$23*(1+Assumptions!$E$7)^5)-((Assumptions!$B$23*(1+Assumptions!$E$7)^5)*Assumptions!$E$8)))-((Assumptions!$B$23*(1+Assumptions!$E$7)^5)*Assumptions!$E$9)))-((Assumptions!$B$23*(1+Assumptions!$E$7)^5)*Assumptions!$E$10)))-(Assumptions!$B$26*Assumptions!$E$12)))*Assumptions!$E$11))) -> 3859.5879
A38: Net Margin | B38: =(((((((((((Assumptions!$B$23*(1+Assumptions!$C$7)^5)-((Assumptions!$B$23*(1+Assumptions!$C$7)^5)*Assumptions!$C$8)))-((Assumptions!$B$23*(1+Assumptions!$C$7)^5)*Assumptions!$C$9)))-((Assumptions!$B$23*(1+Assumptions!$C$7)^5)*Assumptions!$C$10)))-(Assumptions!$B$26*Assumptions!$C$12)))-(((((((((((Assumptions!$B$23*(1+Assumptions!$C$7)^5)-((Assumptions!$B$23*(1+Assumptions!$C$7)^5)*Assumptions!$C$8)))-((Assumptions!$B$23*(1+Assumptions!$C$7)^5)*Assumptions!$C$9)))-((Assumptions!$B$23*(1+Assumptions!$C$7)^5)*Assumptions!$C$10)))-(Assumptions!$B$26*Assumptions!$C$12)))*Assumptions!$C$11))))/(Assumptions!$B$23*(1+Assumptions!$C$7)^5) -> 0.1101996 | C38: =(((((((((((Assumptions!$B$23*(1+Assumptions!$D$7)^5)-((Assumptions!$B$23*(1+Assumptions!$D$7)^5)*Assumptions!$D$8)))-((Assumptions!$B$23*(1+Assumptions!$D$7)^5)*Assumptions!$D$9)))-((Assumptions!$B$23*(1+Assumptions!$D$7)^5)*Assumptions!$D$10)))-(Assumptions!$B$26*Assumptions!$D$12)))-(((((((((((Assumptions!$B$23*(1+Assumptions!$D$7)^5)-((Assumptions!$B$23*(1+Assumptions!$D$7)^5)*Assumptions!$D$8)))-((Assumptions!$B$23*(1+Assumptions!$D$7)^5)*Assumptions!$D$9)))-((Assumptions!$B$23*(1+Assumptions!$D$7)^5)*Assumptions!$D$10)))-(Assumptions!$B$26*Assumptions!$D$12)))*Assumptions!$D$11))))/(Assumptions!$B$23*(1+Assumptions!$D$7)^5) -> 0.14484066 | D38: =(((((((((((Assumptions!$B$23*(1+Assumptions!$E$7)^5)-((Assumptions!$B$23*(1+Assumptions!$E$7)^5)*Assumptions!$E$8)))-((Assumptions!$B$23*(1+Assumptions!$E$7)^5)*Assumptions!$E$9)))-((Assumptions!$B$23*(1+Assumptions!$E$7)^5)*Assumptions!$E$10)))-(Assumptions!$B$26*Assumptions!$E$12)))-(((((((((((Assumptions!$B$23*(1+Assumptions!$E$7)^5)-((Assumptions!$B$23*(1+Assumptions!$E$7)^5)*Assumptions!$E$8)))-((Assumptions!$B$23*(1+Assumptions!$E$7)^5)*Assumptions!$E$9)))-((Assumptions!$B$23*(1+Assumptions!$E$7)^5)*Assumptions!$E$10)))-(Assumptions!$B$26*Assumptions!$E$12)))*Assumptions!$E$11))))/(Assumptions!$B$23*(1+Assumptions!$E$7)^5) -> 0.034957476
A40: Note: this table recalculates Year 6 revenue and net income directly from each scenario's own drivers (growth, COGS%, Opex%, depreciation%, interest rate, and tax rate), independent of the scenario selector above — so all three cases are visible at the same time for comparison.

Sheet Assumptions
A1: Simple 3-Statement Model — Assumptions
A2: Legend: blue = input cell (edit these) · yellow = key driver · green = link to another sheet
A4: Scenario Selector | B4: Base
A6: Growth & Margin Drivers | C6: Base | D6: Upside | E6: Downside | F6: Active
A7: Revenue growth, Years 2-6 (%) | C7: 0.08 | D7: 0.15 | E7: 0.02 | F7: =INDEX(C7:E7,MATCH($B$4,$C$6:$E$6,0)) -> 0.08
A8: COGS (% of revenue) | C8: 0.6 | D8: 0.58 | E8: 0.65 | F8: =INDEX(C8:E8,MATCH($B$4,$C$6:$E$6,0)) -> 0.6
A9: Opex (% of revenue) | C9: 0.2 | D9: 0.18 | E9: 0.24 | F9: =INDEX(C9:E9,MATCH($B$4,$C$6:$E$6,0)) -> 0.2
A10: Depreciation (% of revenue) | C10: 0.05 | D10: 0.05 | E10: 0.05 | F10: =INDEX(C10:E10,MATCH($B$4,$C$6:$E$6,0)) -> 0.05
A11: Tax rate (%) | C11: 0.2 | D11: 0.2 | E11: 0.2 | F11: =INDEX(C11:E11,MATCH($B$4,$C$6:$E$6,0)) -> 0.2
A12: Interest rate on debt (%) | C12: 0.06 | D12: 0.06 | E12: 0.06 | F12: =INDEX(C12:E12,MATCH($B$4,$C$6:$E$6,0)) -> 0.06
A15: Working Capital Drivers
A16: Accounts receivable (days) | C16: 30 | D16: 25 | E16: 35 | F16: =INDEX(C16:E16,MATCH($B$4,$C$6:$E$6,0)) -> 30
A17: Inventory (days, based on COGS) | C17: 45 | D17: 40 | E17: 50 | F17: =INDEX(C17:E17,MATCH($B$4,$C$6:$E$6,0)) -> 45
A18: Accounts payable (days, based on COGS) | C18: 40 | D18: 45 | E18: 35 | F18: =INDEX(C18:E18,MATCH($B$4,$C$6:$E$6,0)) -> 40
A20: Capex (fixed $ per year) | C20: 8000 | D20: 10000 | E20: 6000 | F20: =INDEX(C20:E20,MATCH($B$4,$C$6:$E$6,0)) -> 8000
A22: Year 1 (Base/Actual) Balances
A23: Year 1 revenue ($) | B23: 100000
A24: Year 1 ending cash ($) | B24: 15000
A25: Year 1 ending net PP&E ($) | B25: 40000
A26: Year 1 ending debt ($) | B26: 30000
A27: Current portion of debt (%) — 0% = fully long-term (no repayment modeled, consistent with Cash from Financing = 0) | B27: 0
A28: Simplifying assumptions (documented): debt balance is held constant across all years (no new borrowing/repayment, so interest expense is non-circular); no dividends are paid (all net income is retained); tax is applied even if EBT is negative (no NOL carryforward); the same revenue-growth rate is applied to every forecast year within a scenario (a single driver per scenario, not a year-by-year schedule) to keep the model easy to audit.

Sheet Income Statement
A1: Income Statement
A3: ($) | B3: 2026A | C3: 2027E | D3: 2028E | E3: 2029E | F3: 2030E | G3: 2031E
A4: Revenue | B4: =Assumptions!B23 -> 100000 | C4: =B4*(1+Assumptions!$F$7) -> 108000 | D4: =C4*(1+Assumptions!$F$7) -> 116640 | E4: =D4*(1+Assumptions!$F$7) -> 125971.2 | F4: =E4*(1+Assumptions!$F$7) -> 136048.9 | G4: =F4*(1+Assumptions!$F$7) -> 146932.81
A5: COGS | B5: =B4*Assumptions!$C$8 -> 60000 | C5: =C4*Assumptions!$F$8 -> 64800 | D5: =D4*Assumptions!$F$8 -> 69984 | E5: =E4*Assumptions!$F$8 -> 75582.72 | F5: =F4*Assumptions!$F$8 -> 81629.338 | G5: =G4*Assumptions!$F$8 -> 88159.685
A6: Gross Profit | B6: =B4-B5 -> 40000 | C6: =C4-C5 -> 43200 | D6: =D4-D5 -> 46656 | E6: =E4-E5 -> 50388.48 | F6: =F4-F5 -> 54419.558 | G6: =G4-G5 -> 58773.123
A7: Opex | B7: =B4*Assumptions!$C$9 -> 20000 | C7: =C4*Assumptions!$F$9 -> 21600 | D7: =D4*Assumptions!$F$9 -> 23328 | E7: =E4*Assumptions!$F$9 -> 25194.24 | F7: =F4*Assumptions!$F$9 -> 27209.779 | G7: =G4*Assumptions!$F$9 -> 29386.562
A8: EBITDA | B8: =B6-B7 -> 20000 | C8: =C6-C7 -> 21600 | D8: =D6-D7 -> 23328 | E8: =E6-E7 -> 25194.24 | F8: =F6-F7 -> 27209.779 | G8: =G6-G7 -> 29386.562
A9: Depreciation | B9: =B4*Assumptions!$C$10 -> 5000 | C9: =C4*Assumptions!$F$10 -> 5400 | D9: =D4*Assumptions!$F$10 -> 5832 | E9: =E4*Assumptions!$F$10 -> 6298.56 | F9: =F4*Assumptions!$F$10 -> 6802.4448 | G9: =G4*Assumptions!$F$10 -> 7346.6404
A10: EBIT | B10: =B8-B9 -> 15000 | C10: =C8-C9 -> 16200 | D10: =D8-D9 -> 17496 | E10: =E8-E9 -> 18895.68 | F10: =F8-F9 -> 20407.334 | G10: =G8-G9 -> 22039.921
A11: Interest Expense | B11: =Assumptions!$B$26*Assumptions!$C$12 -> 1800 | C11: =Assumptions!$B$26*Assumptions!$F$12 -> 1800 | D11: =Assumptions!$B$26*Assumptions!$F$12 -> 1800 | E11: =Assumptions!$B$26*Assumptions!$F$12 -> 1800 | F11: =Assumptions!$B$26*Assumptions!$F$12 -> 1800 | G11: =Assumptions!$B$26*Assumptions!$F$12 -> 1800
A12: EBT | B12: =B10-B11 -> 13200 | C12: =C10-C11 -> 14400 | D12: =D10-D11 -> 15696 | E12: =E10-E11 -> 17095.68 | F12: =F10-F11 -> 18607.334 | G12: =G10-G11 -> 20239.921
A13: Tax | B13: =B12*Assumptions!$C$11 -> 2640 | C13: =C12*Assumptions!$F$11 -> 2880 | D13: =D12*Assumptions!$F$11 -> 3139.2 | E13: =E12*Assumptions!$F$11 -> 3419.136 | F13: =F12*Assumptions!$F$11 -> 3721.4669 | G13: =G12*Assumptions!$F$11 -> 4047.9842
A14: Net Income | B14: =B12-B13 -> 10560 | C14: =C12-C13 -> 11520 | D14: =D12-D13 -> 12556.8 | E14: =E12-E13 -> 13676.544 | F14: =F12-F13 -> 14885.868 | G14: =G12-G13 -> 16191.937

Sheet Balance Sheet
A1: Balance Sheet
A3: ($) | B3: 2026A | C3: 2027E | D3: 2028E | E3: 2029E | F3: 2030E | G3: 2031E
A4: Cash | B4: =Assumptions!B24 -> 15000 | C4: ='Cash Flow Statement'!C16 -> 23196.712 | D4: ='Cash Flow Statement'!D16 -> 32804.362 | E4: ='Cash Flow Statement'!E16 -> 43935.823 | F4: ='Cash Flow Statement'!F16 -> 56713.001 | G4: ='Cash Flow Statement'!G16 -> 71267.553
A5: Accounts Receivable | B5: ='Income Statement'!B4/365*Assumptions!$C$16 -> 8219.1781 | C5: ='Income Statement'!C4/365*Assumptions!$F$16 -> 8876.7123 | D5: ='Income Statement'!D4/365*Assumptions!$F$16 -> 9586.8493 | E5: ='Income Statement'!E4/365*Assumptions!$F$16 -> 10353.797 | F5: ='Income Statement'!F4/365*Assumptions!$F$16 -> 11182.101 | G5: ='Income Statement'!G4/365*Assumptions!$F$16 -> 12076.669
A6: Inventory | B6: ='Income Statement'!B5/365*Assumptions!$C$17 -> 7397.2603 | C6: ='Income Statement'!C5/365*Assumptions!$F$17 -> 7989.0411 | D6: ='Income Statement'!D5/365*Assumptions!$F$17 -> 8628.1644 | E6: ='Income Statement'!E5/365*Assumptions!$F$17 -> 9318.4175 | F6: ='Income Statement'!F5/365*Assumptions!$F$17 -> 10063.891 | G6: ='Income Statement'!G5/365*Assumptions!$F$17 -> 10869.002
A7: Total Current Assets | B7: =SUM(B4:B6) -> 30616.438 | C7: =SUM(C4:C6) -> 40062.466 | D7: =SUM(D4:D6) -> 51019.375 | E7: =SUM(E4:E6) -> 63608.038 | F7: =SUM(F4:F6) -> 77958.993 | G7: =SUM(G4:G6) -> 94213.225
A8: Net PP&E | B8: =Assumptions!B25 -> 40000 | C8: =B8+Assumptions!$F$20-'Income Statement'!C9 -> 42600 | D8: =C8+Assumptions!$F$20-'Income Statement'!D9 -> 44768 | E8: =D8+Assumptions!$F$20-'Income Statement'!E9 -> 46469.44 | F8: =E8+Assumptions!$F$20-'Income Statement'!F9 -> 47666.995 | G8: =F8+Assumptions!$F$20-'Income Statement'!G9 -> 48320.355
A9: Total Assets | B9: =B7+B8 -> 70616.438 | C9: =C7+C8 -> 82662.466 | D9: =D7+D8 -> 95787.375 | E9: =E7+E8 -> 110077.48 | F9: =F7+F8 -> 125625.99 | G9: =G7+G8 -> 142533.58
A11: Accounts Payable | B11: ='Income Statement'!B5/365*Assumptions!$C$18 -> 6575.3425 | C11: ='Income Statement'!C5/365*Assumptions!$F$18 -> 7101.3699 | D11: ='Income Statement'!D5/365*Assumptions!$F$18 -> 7669.4795 | E11: ='Income Statement'!E5/365*Assumptions!$F$18 -> 8283.0378 | F11: ='Income Statement'!F5/365*Assumptions!$F$18 -> 8945.6808 | G11: ='Income Statement'!G5/365*Assumptions!$F$18 -> 9661.3353
A12: Current Portion of Debt | B12: =Assumptions!$B$26*Assumptions!$B$27 -> 0 | C12: =Assumptions!$B$26*Assumptions!$B$27 -> 0 | D12: =Assumptions!$B$26*Assumptions!$B$27 -> 0 | E12: =Assumptions!$B$26*Assumptions!$B$27 -> 0 | F12: =Assumptions!$B$26*Assumptions!$B$27 -> 0 | G12: =Assumptions!$B$26*Assumptions!$B$27 -> 0
A13: Total Current Liabilities | B13: =B11+B12 -> 6575.3425 | C13: =C11+C12 -> 7101.3699 | D13: =D11+D12 -> 7669.4795 | E13: =E11+E12 -> 8283.0378 | F13: =F11+F12 -> 8945.6808 | G13: =G11+G12 -> 9661.3353
A14: Long-Term Debt | B14: =Assumptions!$B$26*(1-Assumptions!$B$27) -> 30000 | C14: =Assumptions!$B$26*(1-Assumptions!$B$27) -> 30000 | D14: =Assumptions!$B$26*(1-Assumptions!$B$27) -> 30000 | E14: =Assumptions!$B$26*(1-Assumptions!$B$27) -> 30000 | F14: =Assumptions!$B$26*(1-Assumptions!$B$27) -> 30000 | G14: =Assumptions!$B$26*(1-Assumptions!$B$27) -> 30000
A15: Total Liabilities | B15: =B13+B14 -> 36575.342 | C15: =C13+C14 -> 37101.37 | D15: =D13+D14 -> 37669.479 | E15: =E13+E14 -> 38283.038 | F15: =F13+F14 -> 38945.681 | G15: =G13+G14 -> 39661.335
A16: Equity | B16: =B9-B15 -> 34041.096 | C16: =B16+'Income Statement'!C14 -> 45561.096 | D16: =C16+'Income Statement'!D14 -> 58117.896 | E16: =D16+'Income Statement'!E14 -> 71794.44 | F16: =E16+'Income Statement'!F14 -> 86680.307 | G16: =F16+'Income Statement'!G14 -> 102872.24
A17: Total Liabilities + Equity | B17: =B15+B16 -> 70616.438 | C17: =C15+C16 -> 82662.466 | D17: =D15+D16 -> 95787.375 | E17: =E15+E16 -> 110077.48 | F17: =F15+F16 -> 125625.99 | G17: =G15+G16 -> 142533.58
A19: Check (Assets - Liab&Eq) | B19: =B9-B17 -> 0 | C19: =C9-C17 -> 0 | D19: =D9-D17 -> 0 | E19: =E9-E17 -> 0 | F19: =F9-F17 -> 0 | G19: =G9-G17 -> 0

Sheet Cash Flow Statement
A1: Cash Flow Statement
A2: Year 1 is the actual/base year, so no cash flow build is shown for it.
A4: ($) | C4: ='Income Statement'!C3 -> 2027E | D4: ='Income Statement'!D3 -> 2028E | E4: ='Income Statement'!E3 -> 2029E | F4: ='Income Statement'!F3 -> 2030E | G4: ='Income Statement'!G3 -> 2031E
A5: Net Income | C5: ='Income Statement'!C14 -> 11520 | D5: ='Income Statement'!D14 -> 12556.8 | E5: ='Income Statement'!E14 -> 13676.544 | F5: ='Income Statement'!F14 -> 14885.868 | G5: ='Income Statement'!G14 -> 16191.937
A6: + Depreciation | C6: ='Income Statement'!C9 -> 5400 | D6: ='Income Statement'!D9 -> 5832 | E6: ='Income Statement'!E9 -> 6298.56 | F6: ='Income Statement'!F9 -> 6802.4448 | G6: ='Income Statement'!G9 -> 7346.6404
A7: (Increase) in Accounts Receivable | C7: =-('Balance Sheet'!C5-'Balance Sheet'!B5) -> -657.53425 | D7: =-('Balance Sheet'!D5-'Balance Sheet'!C5) -> -710.13699 | E7: =-('Balance Sheet'!E5-'Balance Sheet'!D5) -> -766.94795 | F7: =-('Balance Sheet'!F5-'Balance Sheet'!E5) -> -828.30378 | G7: =-('Balance Sheet'!G5-'Balance Sheet'!F5) -> -894.56808
A8: (Increase) in Inventory | C8: =-('Balance Sheet'!C6-'Balance Sheet'!B6) -> -591.78082 | D8: =-('Balance Sheet'!D6-'Balance Sheet'!C6) -> -639.12329 | E8: =-('Balance Sheet'!E6-'Balance Sheet'!D6) -> -690.25315 | F8: =-('Balance Sheet'!F6-'Balance Sheet'!E6) -> -745.4734 | G8: =-('Balance Sheet'!G6-'Balance Sheet'!F6) -> -805.11127
A9: Increase in Accounts Payable | C9: ='Balance Sheet'!C11-'Balance Sheet'!B11 -> 526.0274 | D9: ='Balance Sheet'!D11-'Balance Sheet'!C11 -> 568.10959 | E9: ='Balance Sheet'!E11-'Balance Sheet'!D11 -> 613.55836 | F9: ='Balance Sheet'!F11-'Balance Sheet'!E11 -> 662.64302 | G9: ='Balance Sheet'!G11-'Balance Sheet'!F11 -> 715.65447
A10: Cash from Operations | C10: =SUM(C5:C9) -> 16196.712 | D10: =SUM(D5:D9) -> 17607.649 | E10: =SUM(E5:E9) -> 19131.461 | F10: =SUM(F5:F9) -> 20777.178 | G10: =SUM(G5:G9) -> 22554.552
A11: Capex | C11: =-Assumptions!$F$20 -> -8000 | D11: =-Assumptions!$F$20 -> -8000 | E11: =-Assumptions!$F$20 -> -8000 | F11: =-Assumptions!$F$20 -> -8000 | G11: =-Assumptions!$F$20 -> -8000
A12: Cash from Investing | C12: =C11 -> -8000 | D12: =D11 -> -8000 | E12: =E11 -> -8000 | F12: =F11 -> -8000 | G12: =G11 -> -8000
A13: Cash from Financing | C13: 0 | D13: 0 | E13: 0 | F13: 0 | G13: 0
A14: Net Change in Cash | C14: =C10+C12+C13 -> 8196.7123 | D14: =D10+D12+D13 -> 9607.6493 | E14: =E10+E12+E13 -> 11131.461 | F14: =F10+F12+F13 -> 12777.178 | G14: =G10+G12+G13 -> 14554.552
A15: Beginning Cash | C15: ='Balance Sheet'!B4 -> 15000 | D15: ='Balance Sheet'!C4 -> 23196.712 | E15: ='Balance Sheet'!D4 -> 32804.362 | F15: ='Balance Sheet'!E4 -> 43935.823 | G15: ='Balance Sheet'!F4 -> 56713.001
A16: Ending Cash | C16: =C15+C14 -> 23196.712 | D16: =D15+D14 -> 32804.362 | E16: =E15+E14 -> 43935.823 | F16: =F15+F14 -> 56713.001 | G16: =G15+G14 -> 71267.553

Sheet Ratios & KPIs
A1: Ratios & KPIs
A2: ="Active scenario: "&Assumptions!$B$4 -> Active scenario: Base
B4: 2026A | C4: 2027E | D4: 2028E | E4: 2029E | F4: 2030E | G4: 2031E
A5: Revenue Growth (%) | B5: n/a | C5: ='Income Statement'!C4/'Income Statement'!B4-1 -> 0.08 | D5: ='Income Statement'!D4/'Income Statement'!C4-1 -> 0.08 | E5: ='Income Statement'!E4/'Income Statement'!D4-1 -> 0.08 | F5: ='Income Statement'!F4/'Income Statement'!E4-1 -> 0.08 | G5: ='Income Statement'!G4/'Income Statement'!F4-1 -> 0.08
A6: Gross Margin (%) | B6: ='Income Statement'!B6/'Income Statement'!B4 -> 0.4 | C6: ='Income Statement'!C6/'Income Statement'!C4 -> 0.4 | D6: ='Income Statement'!D6/'Income Statement'!D4 -> 0.4 | E6: ='Income Statement'!E6/'Income Statement'!E4 -> 0.4 | F6: ='Income Statement'!F6/'Income Statement'!F4 -> 0.4 | G6: ='Income Statement'!G6/'Income Statement'!G4 -> 0.4
A7: EBITDA Margin (%) | B7: ='Income Statement'!B8/'Income Statement'!B4 -> 0.2 | C7: ='Income Statement'!C8/'Income Statement'!C4 -> 0.2 | D7: ='Income Statement'!D8/'Income Statement'!D4 -> 0.2 | E7: ='Income Statement'!E8/'Income Statement'!E4 -> 0.2 | F7: ='Income Statement'!F8/'Income Statement'!F4 -> 0.2 | G7: ='Income Statement'!G8/'Income Statement'!G4 -> 0.2
A8: Net Margin (%) | B8: ='Income Statement'!B14/'Income Statement'!B4 -> 0.1056 | C8: ='Income Statement'!C14/'Income Statement'!C4 -> 0.10666667 | D8: ='Income Statement'!D14/'Income Statement'!D4 -> 0.10765432 | E8: ='Income Statement'!E14/'Income Statement'!E4 -> 0.10856882 | F8: ='Income Statement'!F14/'Income Statement'!F4 -> 0.10941557 | G8: ='Income Statement'!G14/'Income Statement'!G4 -> 0.1101996
A9: Current Ratio (x) | B9: ='Balance Sheet'!B7/'Balance Sheet'!B13 -> 4.65625 | C9: ='Balance Sheet'!C7/'Balance Sheet'!C13 -> 5.6415123 | D9: ='Balance Sheet'!D7/'Balance Sheet'!D13 -> 6.6522605 | E9: ='Balance Sheet'!E7/'Balance Sheet'!E13 -> 7.6793127 | F9: ='Balance Sheet'!F7/'Balance Sheet'!F13 -> 8.7147076 | G9: ='Balance Sheet'!G7/'Balance Sheet'!G13 -> 9.7515739
A10: Debt / Equity (x) | B10: =('Balance Sheet'!B12+'Balance Sheet'!B14)/'Balance Sheet'!B16 -> 0.88128773 | C10: =('Balance Sheet'!C12+'Balance Sheet'!C14)/'Balance Sheet'!C16 -> 0.65845651 | D10: =('Balance Sheet'!D12+'Balance Sheet'!D14)/'Balance Sheet'!D16 -> 0.51619212 | E10: =('Balance Sheet'!E12+'Balance Sheet'!E14)/'Balance Sheet'!E16 -> 0.41785966 | F10: =('Balance Sheet'!F12+'Balance Sheet'!F14)/'Balance Sheet'!F16 -> 0.34609937 | G10: =('Balance Sheet'!G12+'Balance Sheet'!G14)/'Balance Sheet'!G16 -> 0.29162385
A11: Days Sales Outstanding (AR) | B11: ='Balance Sheet'!B5/'Income Statement'!B4*365 -> 30 | C11: ='Balance Sheet'!C5/'Income Statement'!C4*365 -> 30 | D11: ='Balance Sheet'!D5/'Income Statement'!D4*365 -> 30 | E11: ='Balance Sheet'!E5/'Income Statement'!E4*365 -> 30 | F11: ='Balance Sheet'!F5/'Income Statement'!F4*365 -> 30 | G11: ='Balance Sheet'!G5/'Income Statement'!G4*365 -> 30
A12: Days Inventory Outstanding | B12: ='Balance Sheet'!B6/'Income Statement'!B5*365 -> 45 | C12: ='Balance Sheet'!C6/'Income Statement'!C5*365 -> 45 | D12: ='Balance Sheet'!D6/'Income Statement'!D5*365 -> 45 | E12: ='Balance Sheet'!E6/'Income Statement'!E5*365 -> 45 | F12: ='Balance Sheet'!F6/'Income Statement'!F5*365 -> 45 | G12: ='Balance Sheet'!G6/'Income Statement'!G5*365 -> 45
A13: Days Payable Outstanding | B13: ='Balance Sheet'!B11/'Income Statement'!B5*365 -> 40 | C13: ='Balance Sheet'!C11/'Income Statement'!C5*365 -> 40 | D13: ='Balance Sheet'!D11/'Income Statement'!D5*365 -> 40 | E13: ='Balance Sheet'!E11/'Income Statement'!E5*365 -> 40 | F13: ='Balance Sheet'!F11/'Income Statement'!F5*365 -> 40 | G13: ='Balance Sheet'!G11/'Income Statement'!G5*365 -> 40
A15: Model Integrity Checks
A16: Balance Sheet Check (should be 0) | B16: ='Balance Sheet'!B19 -> 0 | C16: ='Balance Sheet'!C19 -> 0 | D16: ='Balance Sheet'!D19 -> 0 | E16: ='Balance Sheet'!E19 -> 0 | F16: ='Balance Sheet'!F19 -> 0 | G16: ='Balance Sheet'!G19 -> 0
A17: Ending Cash = Balance Sheet Cash (should be 0) | B17: n/a | C17: ='Balance Sheet'!C4-'Cash Flow Statement'!C16 -> 0 | D17: ='Balance Sheet'!D4-'Cash Flow Statement'!D16 -> 0 | E17: ='Balance Sheet'!E4-'Cash Flow Statement'!E16 -> 0 | F17: ='Balance Sheet'!F4-'Cash Flow Statement'!F16 -> 0 | G17: ='Balance Sheet'!G4-'Cash Flow Statement'!G16 -> 0

Sheet Monthly Forecast
A1: Monthly Forecast (12M) — 2027 Budget
A2: This is the first forecast year (2027E) split evenly across 12 months (annual / 12, no seasonality assumed), so the Full Year Total below always ties exactly to the 2027 Base Budget figures. It is based on the Base assumptions and independent of the scenario selector — because this is the Budget that Actual results get measured against. Note: if you edit the Base column values in Assumptions, this Budget will reflect that edit too — it is not a frozen historical snapshot, just decoupled from the Upside/Downside toggle.
B7: M1 | C7: M2 | D7: M3 | E7: M4 | F7: M5 | G7: M6 | H7: M7 | I7: M8 | J7: M9 | K7: M10 | L7: M11 | M7: M12 | N7: FY Total
A8: Revenue | B8: =Assumptions!$B$23*(1+Assumptions!$C$7)/12 -> 9000 | C8: =Assumptions!$B$23*(1+Assumptions!$C$7)/12 -> 9000 | D8: =Assumptions!$B$23*(1+Assumptions!$C$7)/12 -> 9000 | E8: =Assumptions!$B$23*(1+Assumptions!$C$7)/12 -> 9000 | F8: =Assumptions!$B$23*(1+Assumptions!$C$7)/12 -> 9000 | G8: =Assumptions!$B$23*(1+Assumptions!$C$7)/12 -> 9000 | H8: =Assumptions!$B$23*(1+Assumptions!$C$7)/12 -> 9000 | I8: =Assumptions!$B$23*(1+Assumptions!$C$7)/12 -> 9000 | ... M8: =Assumptions!$B$23*(1+Assumptions!$C$7)/12 -> 9000 | N8: =SUM(B8:M8) -> 108000
A9: COGS | B9: =B8*Assumptions!$C$8 -> 5400 | C9: =C8*Assumptions!$C$8 -> 5400 | D9: =D8*Assumptions!$C$8 -> 5400 | E9: =E8*Assumptions!$C$8 -> 5400 | F9: =F8*Assumptions!$C$8 -> 5400 | G9: =G8*Assumptions!$C$8 -> 5400 | H9: =H8*Assumptions!$C$8 -> 5400 | I9: =I8*Assumptions!$C$8 -> 5400 | ... M9: =M8*Assumptions!$C$8 -> 5400 | N9: =SUM(B9:M9) -> 64800
A10: Gross Profit | B10: =B8-B9 -> 3600 | C10: =C8-C9 -> 3600 | D10: =D8-D9 -> 3600 | E10: =E8-E9 -> 3600 | F10: =F8-F9 -> 3600 | G10: =G8-G9 -> 3600 | H10: =H8-H9 -> 3600 | I10: =I8-I9 -> 3600 | ... M10: =M8-M9 -> 3600 | N10: =SUM(B10:M10) -> 43200
A11: Opex | B11: =B8*Assumptions!$C$9 -> 1800 | C11: =C8*Assumptions!$C$9 -> 1800 | D11: =D8*Assumptions!$C$9 -> 1800 | E11: =E8*Assumptions!$C$9 -> 1800 | F11: =F8*Assumptions!$C$9 -> 1800 | G11: =G8*Assumptions!$C$9 -> 1800 | H11: =H8*Assumptions!$C$9 -> 1800 | I11: =I8*Assumptions!$C$9 -> 1800 | ... M11: =M8*Assumptions!$C$9 -> 1800 | N11: =SUM(B11:M11) -> 21600
A12: EBITDA | B12: =B10-B11 -> 1800 | C12: =C10-C11 -> 1800 | D12: =D10-D11 -> 1800 | E12: =E10-E11 -> 1800 | F12: =F10-F11 -> 1800 | G12: =G10-G11 -> 1800 | H12: =H10-H11 -> 1800 | I12: =I10-I11 -> 1800 | ... M12: =M10-M11 -> 1800 | N12: =SUM(B12:M12) -> 21600
A13: Depreciation | B13: =B8*Assumptions!$C$10 -> 450 | C13: =C8*Assumptions!$C$10 -> 450 | D13: =D8*Assumptions!$C$10 -> 450 | E13: =E8*Assumptions!$C$10 -> 450 | F13: =F8*Assumptions!$C$10 -> 450 | G13: =G8*Assumptions!$C$10 -> 450 | H13: =H8*Assumptions!$C$10 -> 450 | I13: =I8*Assumptions!$C$10 -> 450 | ... M13: =M8*Assumptions!$C$10 -> 450 | N13: =SUM(B13:M13) -> 5400
A14: EBIT | B14: =B12-B13 -> 1350 | C14: =C12-C13 -> 1350 | D14: =D12-D13 -> 1350 | E14: =E12-E13 -> 1350 | F14: =F12-F13 -> 1350 | G14: =G12-G13 -> 1350 | H14: =H12-H13 -> 1350 | I14: =I12-I13 -> 1350 | ... M14: =M12-M13 -> 1350 | N14: =SUM(B14:M14) -> 16200
A15: Interest Expense | B15: =Assumptions!$B$26*Assumptions!$C$12/12 -> 150 | C15: =Assumptions!$B$26*Assumptions!$C$12/12 -> 150 | D15: =Assumptions!$B$26*Assumptions!$C$12/12 -> 150 | E15: =Assumptions!$B$26*Assumptions!$C$12/12 -> 150 | F15: =Assumptions!$B$26*Assumptions!$C$12/12 -> 150 | G15: =Assumptions!$B$26*Assumptions!$C$12/12 -> 150 | H15: =Assumptions!$B$26*Assumptions!$C$12/12 -> 150 | I15: =Assumptions!$B$26*Assumptions!$C$12/12 -> 150 | ... M15: =Assumptions!$B$26*Assumptions!$C$12/12 -> 150 | N15: =SUM(B15:M15) -> 1800
A16: EBT | B16: =B14-B15 -> 1200 | C16: =C14-C15 -> 1200 | D16: =D14-D15 -> 1200 | E16: =E14-E15 -> 1200 | F16: =F14-F15 -> 1200 | G16: =G14-G15 -> 1200 | H16: =H14-H15 -> 1200 | I16: =I14-I15 -> 1200 | ... M16: =M14-M15 -> 1200 | N16: =SUM(B16:M16) -> 14400
A17: Tax | B17: =B16*Assumptions!$C$11 -> 240 | C17: =C16*Assumptions!$C$11 -> 240 | D17: =D16*Assumptions!$C$11 -> 240 | E17: =E16*Assumptions!$C$11 -> 240 | F17: =F16*Assumptions!$C$11 -> 240 | G17: =G16*Assumptions!$C$11 -> 240 | H17: =H16*Assumptions!$C$11 -> 240 | I17: =I16*Assumptions!$C$11 -> 240 | ... M17: =M16*Assumptions!$C$11 -> 240 | N17: =SUM(B17:M17) -> 2880
A18: Net Income | B18: =B16-B17 -> 960 | C18: =C16-C17 -> 960 | D18: =D16-D17 -> 960 | E18: =E16-E17 -> 960 | F18: =F16-F17 -> 960 | G18: =G16-G17 -> 960 | H18: =H16-H17 -> 960 | I18: =I16-I17 -> 960 | ... M18: =M16-M17 -> 960 | N18: =SUM(B18:M18) -> 11520
A20: Budget Tie Check (Monthly Total vs. Annual Base Model — should be 0) | B20: =N8-(Assumptions!$B$23*(1+Assumptions!$C$7)) -> 0 | C20: <- Revenue
B21: =N18-((Assumptions!$B$23*(1+Assumptions!$C$7)-Assumptions!$B$23*(1+Assumptions!$C$7)*Assumptions!$C$8-Assumptions!$B$23*(1+Assumptions!$C$7)*Assumptions!$C$9-Assumptions!$B$23*(1+Assumptions!$C$7)*Assumptions!$C$10-Assumptions!$B$26*Assumptions!$C$12)*(1-Assumptions!$C$11)) -> 0 | C21: <- Net Income

Sheet Actual vs Budget vs Forecast
A1: Actual vs. Budget vs. Latest Estimate — 2027
A2: Budget = the Monthly Forecast plan (based on Base assumptions). Enter real monthly results in the blue Actual rows (Revenue, COGS, Opex) as each month closes — leave future months blank. Gross Profit, EBITDA, and Net Income are then derived automatically. "Latest Estimate" = Actual for closed months + remaining Budget for open months (a common FP&A shortcut — not a full re-forecast, since open months aren't given new assumptions of their own). For COGS and Opex, a NEGATIVE variance means actual cost came in BELOW budget — that's favorable, the opposite of Revenue/Profit lines.
B5: M1 | C5: M2 | D5: M3 | E5: M4 | F5: M5 | G5: M6 | H5: M7 | I5: M8 | J5: M9 | K5: M10 | L5: M11 | M5: M12 | N5: FY / YTD
A7: Revenue
A8: Budget | B8: ='Monthly Forecast'!B8 -> 9000 | C8: ='Monthly Forecast'!C8 -> 9000 | D8: ='Monthly Forecast'!D8 -> 9000 | E8: ='Monthly Forecast'!E8 -> 9000 | F8: ='Monthly Forecast'!F8 -> 9000 | G8: ='Monthly Forecast'!G8 -> 9000 | H8: ='Monthly Forecast'!H8 -> 9000 | I8: ='Monthly Forecast'!I8 -> 9000 | ... M8: ='Monthly Forecast'!M8 -> 9000 | N8: =SUM(B8:M8) -> 108000
A9: Actual (enter here) | N9: =IF(COUNT(B9:M9)=0,"",SUM(B9:M9))
A10: Latest Estimate | B10: =IF(ISBLANK(B9),B8,B9) -> 9000 | C10: =IF(ISBLANK(C9),C8,C9) -> 9000 | D10: =IF(ISBLANK(D9),D8,D9) -> 9000 | E10: =IF(ISBLANK(E9),E8,E9) -> 9000 | F10: =IF(ISBLANK(F9),F8,F9) -> 9000 | G10: =IF(ISBLANK(G9),G8,G9) -> 9000 | H10: =IF(ISBLANK(H9),H8,H9) -> 9000 | I10: =IF(ISBLANK(I9),I8,I9) -> 9000 | ... M10: =IF(ISBLANK(M9),M8,M9) -> 9000 | N10: =SUM(B10:M10) -> 108000
A11: Variance ($) | B11: =IF(ISBLANK(B9),"n/a",B9-B8) -> n/a | C11: =IF(ISBLANK(C9),"n/a",C9-C8) -> n/a | D11: =IF(ISBLANK(D9),"n/a",D9-D8) -> n/a | E11: =IF(ISBLANK(E9),"n/a",E9-E8) -> n/a | F11: =IF(ISBLANK(F9),"n/a",F9-F8) -> n/a | G11: =IF(ISBLANK(G9),"n/a",G9-G8) -> n/a | H11: =IF(ISBLANK(H9),"n/a",H9-H8) -> n/a | I11: =IF(ISBLANK(I9),"n/a",I9-I8) -> n/a | ... M11: =IF(ISBLANK(M9),"n/a",M9-M8) -> n/a | N11: =IF(COUNT($B$9:$M$9)=0,"n/a",SUM(B9:M9)-SUMIF($B$9:$M$9,"<>",B8:M8)) -> n/a
A12: Variance (%) | B12: =IF(ISBLANK(B9),"n/a",IF(B8=0,"n/a",(B9-B8)/B8)) -> n/a | C12: =IF(ISBLANK(C9),"n/a",IF(C8=0,"n/a",(C9-C8)/C8)) -> n/a | D12: =IF(ISBLANK(D9),"n/a",IF(D8=0,"n/a",(D9-D8)/D8)) -> n/a | E12: =IF(ISBLANK(E9),"n/a",IF(E8=0,"n/a",(E9-E8)/E8)) -> n/a | F12: =IF(ISBLANK(F9),"n/a",IF(F8=0,"n/a",(F9-F8)/F8)) -> n/a | G12: =IF(ISBLANK(G9),"n/a",IF(G8=0,"n/a",(G9-G8)/G8)) -> n/a | H12: =IF(ISBLANK(H9),"n/a",IF(H8=0,"n/a",(H9-H8)/H8)) -> n/a | I12: =IF(ISBLANK(I9),"n/a",IF(I8=0,"n/a",(I9-I8)/I8)) -> n/a | ... M12: =IF(ISBLANK(M9),"n/a",IF(M8=0,"n/a",(M9-M8)/M8)) -> n/a | N12: =IF(N11="n/a","n/a",N11/SUMIF($B$9:$M$9,"<>",B8:M8)) -> n/a
A14: COGS
A15: Budget | B15: ='Monthly Forecast'!B9 -> 5400 | C15: ='Monthly Forecast'!C9 -> 5400 | D15: ='Monthly Forecast'!D9 -> 5400 | E15: ='Monthly Forecast'!E9 -> 5400 | F15: ='Monthly Forecast'!F9 -> 5400 | G15: ='Monthly Forecast'!G9 -> 5400 | H15: ='Monthly Forecast'!H9 -> 5400 | I15: ='Monthly Forecast'!I9 -> 5400 | ... M15: ='Monthly Forecast'!M9 -> 5400 | N15: =SUM(B15:M15) -> 64800
A16: Actual (enter here) | N16: =IF(COUNT(B16:M16)=0,"",SUM(B16:M16))
A17: Latest Estimate | B17: =IF(ISBLANK(B16),B15,B16) -> 5400 | C17: =IF(ISBLANK(C16),C15,C16) -> 5400 | D17: =IF(ISBLANK(D16),D15,D16) -> 5400 | E17: =IF(ISBLANK(E16),E15,E16) -> 5400 | F17: =IF(ISBLANK(F16),F15,F16) -> 5400 | G17: =IF(ISBLANK(G16),G15,G16) -> 5400 | H17: =IF(ISBLANK(H16),H15,H16) -> 5400 | I17: =IF(ISBLANK(I16),I15,I16) -> 5400 | ... M17: =IF(ISBLANK(M16),M15,M16) -> 5400 | N17: =SUM(B17:M17) -> 64800
A18: Variance ($) | B18: =IF(ISBLANK(B16),"n/a",B16-B15) -> n/a | C18: =IF(ISBLANK(C16),"n/a",C16-C15) -> n/a | D18: =IF(ISBLANK(D16),"n/a",D16-D15) -> n/a | E18: =IF(ISBLANK(E16),"n/a",E16-E15) -> n/a | F18: =IF(ISBLANK(F16),"n/a",F16-F15) -> n/a | G18: =IF(ISBLANK(G16),"n/a",G16-G15) -> n/a | H18: =IF(ISBLANK(H16),"n/a",H16-H15) -> n/a | I18: =IF(ISBLANK(I16),"n/a",I16-I15) -> n/a | ... M18: =IF(ISBLANK(M16),"n/a",M16-M15) -> n/a | N18: =IF(COUNT($B$9:$M$9)=0,"n/a",SUM(B16:M16)-SUMIF($B$9:$M$9,"<>",B15:M15)) -> n/a
A19: Variance (%) | B19: =IF(ISBLANK(B16),"n/a",IF(B15=0,"n/a",(B16-B15)/B15)) -> n/a | C19: =IF(ISBLANK(C16),"n/a",IF(C15=0,"n/a",(C16-C15)/C15)) -> n/a | D19: =IF(ISBLANK(D16),"n/a",IF(D15=0,"n/a",(D16-D15)/D15)) -> n/a | E19: =IF(ISBLANK(E16),"n/a",IF(E15=0,"n/a",(E16-E15)/E15)) -> n/a | F19: =IF(ISBLANK(F16),"n/a",IF(F15=0,"n/a",(F16-F15)/F15)) -> n/a | G19: =IF(ISBLANK(G16),"n/a",IF(G15=0,"n/a",(G16-G15)/G15)) -> n/a | H19: =IF(ISBLANK(H16),"n/a",IF(H15=0,"n/a",(H16-H15)/H15)) -> n/a | I19: =IF(ISBLANK(I16),"n/a",IF(I15=0,"n/a",(I16-I15)/I15)) -> n/a | ... M19: =IF(ISBLANK(M16),"n/a",IF(M15=0,"n/a",(M16-M15)/M15)) -> n/a | N19: =IF(N18="n/a","n/a",N18/SUMIF($B$9:$M$9,"<>",B15:M15)) -> n/a
A21: Gross Profit
A22: Budget | B22: =B8-B15 -> 3600 | C22: =C8-C15 -> 3600 | D22: =D8-D15 -> 3600 | E22: =E8-E15 -> 3600 | F22: =F8-F15 -> 3600 | G22: =G8-G15 -> 3600 | H22: =H8-H15 -> 3600 | I22: =I8-I15 -> 3600 | ... M22: =M8-M15 -> 3600 | N22: =SUM(B22:M22) -> 43200
A23: Actual (derived) | B23: =IF(OR(ISBLANK(B9),ISBLANK(B16)),"",B9-B16) | C23: =IF(OR(ISBLANK(C9),ISBLANK(C16)),"",C9-C16) | D23: =IF(OR(ISBLANK(D9),ISBLANK(D16)),"",D9-D16) | E23: =IF(OR(ISBLANK(E9),ISBLANK(E16)),"",E9-E16) | F23: =IF(OR(ISBLANK(F9),ISBLANK(F16)),"",F9-F16) | G23: =IF(OR(ISBLANK(G9),ISBLANK(G16)),"",G9-G16) | H23: =IF(OR(ISBLANK(H9),ISBLANK(H16)),"",H9-H16) | I23: =IF(OR(ISBLANK(I9),ISBLANK(I16)),"",I9-I16) | ... M23: =IF(OR(ISBLANK(M9),ISBLANK(M16)),"",M9-M16) | N23: =IF(COUNT($B$9:$M$9)=0,"",SUM(B23:M23))
A24: Latest Estimate | B24: =IF(OR(ISBLANK(B9),ISBLANK(B16)),B22,B23) -> 3600 | C24: =IF(OR(ISBLANK(C9),ISBLANK(C16)),C22,C23) -> 3600 | D24: =IF(OR(ISBLANK(D9),ISBLANK(D16)),D22,D23) -> 3600 | E24: =IF(OR(ISBLANK(E9),ISBLANK(E16)),E22,E23) -> 3600 | F24: =IF(OR(ISBLANK(F9),ISBLANK(F16)),F22,F23) -> 3600 | G24: =IF(OR(ISBLANK(G9),ISBLANK(G16)),G22,G23) -> 3600 | H24: =IF(OR(ISBLANK(H9),ISBLANK(H16)),H22,H23) -> 3600 | I24: =IF(OR(ISBLANK(I9),ISBLANK(I16)),I22,I23) -> 3600 | ... M24: =IF(OR(ISBLANK(M9),ISBLANK(M16)),M22,M23) -> 3600 | N24: =SUM(B24:M24) -> 43200
A25: Variance ($) | B25: =IF(OR(ISBLANK(B9),ISBLANK(B16)),"n/a",B23-B22) -> n/a | C25: =IF(OR(ISBLANK(C9),ISBLANK(C16)),"n/a",C23-C22) -> n/a | D25: =IF(OR(ISBLANK(D9),ISBLANK(D16)),"n/a",D23-D22) -> n/a | E25: =IF(OR(ISBLANK(E9),ISBLANK(E16)),"n/a",E23-E22) -> n/a | F25: =IF(OR(ISBLANK(F9),ISBLANK(F16)),"n/a",F23-F22) -> n/a | G25: =IF(OR(ISBLANK(G9),ISBLANK(G16)),"n/a",G23-G22) -> n/a | H25: =IF(OR(ISBLANK(H9),ISBLANK(H16)),"n/a",H23-H22) -> n/a | I25: =IF(OR(ISBLANK(I9),ISBLANK(I16)),"n/a",I23-I22) -> n/a | ... M25: =IF(OR(ISBLANK(M9),ISBLANK(M16)),"n/a",M23-M22) -> n/a | N25: =IF(COUNT($B$9:$M$9)=0,"n/a",N23-SUMIF($B$9:$M$9,"<>",B22:M22)) -> n/a
A26: Variance (%) | B26: =IF(OR(ISBLANK(B9),ISBLANK(B16)),"n/a",IF(B22=0,"n/a",(B23-B22)/B22)) -> n/a | C26: =IF(OR(ISBLANK(C9),ISBLANK(C16)),"n/a",IF(C22=0,"n/a",(C23-C22)/C22)) -> n/a | D26: =IF(OR(ISBLANK(D9),ISBLANK(D16)),"n/a",IF(D22=0,"n/a",(D23-D22)/D22)) -> n/a | E26: =IF(OR(ISBLANK(E9),ISBLANK(E16)),"n/a",IF(E22=0,"n/a",(E23-E22)/E22)) -> n/a | F26: =IF(OR(ISBLANK(F9),ISBLANK(F16)),"n/a",IF(F22=0,"n/a",(F23-F22)/F22)) -> n/a | G26: =IF(OR(ISBLANK(G9),ISBLANK(G16)),"n/a",IF(G22=0,"n/a",(G23-G22)/G22)) -> n/a | H26: =IF(OR(ISBLANK(H9),ISBLANK(H16)),"n/a",IF(H22=0,"n/a",(H23-H22)/H22)) -> n/a | I26: =IF(OR(ISBLANK(I9),ISBLANK(I16)),"n/a",IF(I22=0,"n/a",(I23-I22)/I22)) -> n/a | ... M26: =IF(OR(ISBLANK(M9),ISBLANK(M16)),"n/a",IF(M22=0,"n/a",(M23-M22)/M22)) -> n/a | N26: =IF(N25="n/a","n/a",N25/SUMIF($B$9:$M$9,"<>",B22:M22)) -> n/a
A28: Gross Margin %
A29: Budget % | B29: =IF(B8=0,"n/a",B22/B8) -> 0.4 | C29: =IF(C8=0,"n/a",C22/C8) -> 0.4 | D29: =IF(D8=0,"n/a",D22/D8) -> 0.4 | E29: =IF(E8=0,"n/a",E22/E8) -> 0.4 | F29: =IF(F8=0,"n/a",F22/F8) -> 0.4 | G29: =IF(G8=0,"n/a",G22/G8) -> 0.4 | H29: =IF(H8=0,"n/a",H22/H8) -> 0.4 | I29: =IF(I8=0,"n/a",I22/I8) -> 0.4 | ... N29: =IF(N8=0,"n/a",N22/N8) -> 0.4
A30: Actual % | B30: =IF(OR(ISBLANK(B9),ISBLANK(B16)),"n/a",IF(B9=0,"n/a",B23/B9)) -> n/a | C30: =IF(OR(ISBLANK(C9),ISBLANK(C16)),"n/a",IF(C9=0,"n/a",C23/C9)) -> n/a | D30: =IF(OR(ISBLANK(D9),ISBLANK(D16)),"n/a",IF(D9=0,"n/a",D23/D9)) -> n/a | E30: =IF(OR(ISBLANK(E9),ISBLANK(E16)),"n/a",IF(E9=0,"n/a",E23/E9)) -> n/a | F30: =IF(OR(ISBLANK(F9),ISBLANK(F16)),"n/a",IF(F9=0,"n/a",F23/F9)) -> n/a | G30: =IF(OR(ISBLANK(G9),ISBLANK(G16)),"n/a",IF(G9=0,"n/a",G23/G9)) -> n/a | H30: =IF(OR(ISBLANK(H9),ISBLANK(H16)),"n/a",IF(H9=0,"n/a",H23/H9)) -> n/a | I30: =IF(OR(ISBLANK(I9),ISBLANK(I16)),"n/a",IF(I9=0,"n/a",I23/I9)) -> n/a | ... M30: =IF(OR(ISBLANK(M9),ISBLANK(M16)),"n/a",IF(M9=0,"n/a",M23/M9)) -> n/a | N30: =IF(COUNT($B$9:$M$9)=0,"n/a",IF(N9=0,"n/a",N23/N9)) -> n/a
A31: Variance (pp) | B31: =IF(B30="n/a","n/a",B30-B29) -> n/a | C31: =IF(C30="n/a","n/a",C30-C29) -> n/a | D31: =IF(D30="n/a","n/a",D30-D29) -> n/a | E31: =IF(E30="n/a","n/a",E30-E29) -> n/a | F31: =IF(F30="n/a","n/a",F30-F29) -> n/a | G31: =IF(G30="n/a","n/a",G30-G29) -> n/a | H31: =IF(H30="n/a","n/a",H30-H29) -> n/a | I31: =IF(I30="n/a","n/a",I30-I29) -> n/a | ... N31: =IF(N30="n/a","n/a",N30-N29) -> n/a
A33: Opex
A34: Budget | B34: ='Monthly Forecast'!B11 -> 1800 | C34: ='Monthly Forecast'!C11 -> 1800 | D34: ='Monthly Forecast'!D11 -> 1800 | E34: ='Monthly Forecast'!E11 -> 1800 | F34: ='Monthly Forecast'!F11 -> 1800 | G34: ='Monthly Forecast'!G11 -> 1800 | H34: ='Monthly Forecast'!H11 -> 1800 | I34: ='Monthly Forecast'!I11 -> 1800 | ... M34: ='Monthly Forecast'!M11 -> 1800 | N34: =SUM(B34:M34) -> 21600
A35: Actual (enter here) | N35: =IF(COUNT(B35:M35)=0,"",SUM(B35:M35))
A36: Latest Estimate | B36: =IF(ISBLANK(B35),B34,B35) -> 1800 | C36: =IF(ISBLANK(C35),C34,C35) -> 1800 | D36: =IF(ISBLANK(D35),D34,D35) -> 1800 | E36: =IF(ISBLANK(E35),E34,E35) -> 1800 | F36: =IF(ISBLANK(F35),F34,F35) -> 1800 | G36: =IF(ISBLANK(G35),G34,G35) -> 1800 | H36: =IF(ISBLANK(H35),H34,H35) -> 1800 | I36: =IF(ISBLANK(I35),I34,I35) -> 1800 | ... M36: =IF(ISBLANK(M35),M34,M35) -> 1800 | N36: =SUM(B36:M36) -> 21600
A37: Variance ($) | B37: =IF(ISBLANK(B35),"n/a",B35-B34) -> n/a | C37: =IF(ISBLANK(C35),"n/a",C35-C34) -> n/a | D37: =IF(ISBLANK(D35),"n/a",D35-D34) -> n/a | E37: =IF(ISBLANK(E35),"n/a",E35-E34) -> n/a | F37: =IF(ISBLANK(F35),"n/a",F35-F34) -> n/a | G37: =IF(ISBLANK(G35),"n/a",G35-G34) -> n/a | H37: =IF(ISBLANK(H35),"n/a",H35-H34) -> n/a | I37: =IF(ISBLANK(I35),"n/a",I35-I34) -> n/a | ... M37: =IF(ISBLANK(M35),"n/a",M35-M34) -> n/a | N37: =IF(COUNT($B$9:$M$9)=0,"n/a",SUM(B35:M35)-SUMIF($B$9:$M$9,"<>",B34:M34)) -> n/a
A38: Variance (%) | B38: =IF(ISBLANK(B35),"n/a",IF(B34=0,"n/a",(B35-B34)/B34)) -> n/a | C38: =IF(ISBLANK(C35),"n/a",IF(C34=0,"n/a",(C35-C34)/C34)) -> n/a | D38: =IF(ISBLANK(D35),"n/a",IF(D34=0,"n/a",(D35-D34)/D34)) -> n/a | E38: =IF(ISBLANK(E35),"n/a",IF(E34=0,"n/a",(E35-E34)/E34)) -> n/a | F38: =IF(ISBLANK(F35),"n/a",IF(F34=0,"n/a",(F35-F34)/F34)) -> n/a | G38: =IF(ISBLANK(G35),"n/a",IF(G34=0,"n/a",(G35-G34)/G34)) -> n/a | H38: =IF(ISBLANK(H35),"n/a",IF(H34=0,"n/a",(H35-H34)/H34)) -> n/a | I38: =IF(ISBLANK(I35),"n/a",IF(I34=0,"n/a",(I35-I34)/I34)) -> n/a | ... M38: =IF(ISBLANK(M35),"n/a",IF(M34=0,"n/a",(M35-M34)/M34)) -> n/a | N38: =IF(N37="n/a","n/a",N37/SUMIF($B$9:$M$9,"<>",B34:M34)) -> n/a
A40: EBITDA
A41: Budget | B41: =B22-B34 -> 1800 | C41: =C22-C34 -> 1800 | D41: =D22-D34 -> 1800 | E41: =E22-E34 -> 1800 | F41: =F22-F34 -> 1800 | G41: =G22-G34 -> 1800 | H41: =H22-H34 -> 1800 | I41: =I22-I34 -> 1800 | ... M41: =M22-M34 -> 1800 | N41: =SUM(B41:M41) -> 21600
A42: Actual (derived) | B42: =IF(OR(ISBLANK(B9),ISBLANK(B16),ISBLANK(B35)),"",B23-B35) | C42: =IF(OR(ISBLANK(C9),ISBLANK(C16),ISBLANK(C35)),"",C23-C35) | D42: =IF(OR(ISBLANK(D9),ISBLANK(D16),ISBLANK(D35)),"",D23-D35) | E42: =IF(OR(ISBLANK(E9),ISBLANK(E16),ISBLANK(E35)),"",E23-E35) | F42: =IF(OR(ISBLANK(F9),ISBLANK(F16),ISBLANK(F35)),"",F23-F35) | G42: =IF(OR(ISBLANK(G9),ISBLANK(G16),ISBLANK(G35)),"",G23-G35) | H42: =IF(OR(ISBLANK(H9),ISBLANK(H16),ISBLANK(H35)),"",H23-H35) | I42: =IF(OR(ISBLANK(I9),ISBLANK(I16),ISBLANK(I35)),"",I23-I35) | ... M42: =IF(OR(ISBLANK(M9),ISBLANK(M16),ISBLANK(M35)),"",M23-M35) | N42: =IF(COUNT($B$9:$M$9)=0,"",SUM(B42:M42))
A43: Latest Estimate | B43: =IF(OR(ISBLANK(B9),ISBLANK(B16),ISBLANK(B35)),B41,B42) -> 1800 | C43: =IF(OR(ISBLANK(C9),ISBLANK(C16),ISBLANK(C35)),C41,C42) -> 1800 | D43: =IF(OR(ISBLANK(D9),ISBLANK(D16),ISBLANK(D35)),D41,D42) -> 1800 | E43: =IF(OR(ISBLANK(E9),ISBLANK(E16),ISBLANK(E35)),E41,E42) -> 1800 | F43: =IF(OR(ISBLANK(F9),ISBLANK(F16),ISBLANK(F35)),F41,F42) -> 1800 | G43: =IF(OR(ISBLANK(G9),ISBLANK(G16),ISBLANK(G35)),G41,G42) -> 1800 | H43: =IF(OR(ISBLANK(H9),ISBLANK(H16),ISBLANK(H35)),H41,H42) -> 1800 | I43: =IF(OR(ISBLANK(I9),ISBLANK(I16),ISBLANK(I35)),I41,I42) -> 1800 | ... M43: =IF(OR(ISBLANK(M9),ISBLANK(M16),ISBLANK(M35)),M41,M42) -> 1800 | N43: =SUM(B43:M43) -> 21600
A44: Variance ($) | B44: =IF(OR(ISBLANK(B9),ISBLANK(B16),ISBLANK(B35)),"n/a",B42-B41) -> n/a | C44: =IF(OR(ISBLANK(C9),ISBLANK(C16),ISBLANK(C35)),"n/a",C42-C41) -> n/a | D44: =IF(OR(ISBLANK(D9),ISBLANK(D16),ISBLANK(D35)),"n/a",D42-D41) -> n/a | E44: =IF(OR(ISBLANK(E9),ISBLANK(E16),ISBLANK(E35)),"n/a",E42-E41) -> n/a | F44: =IF(OR(ISBLANK(F9),ISBLANK(F16),ISBLANK(F35)),"n/a",F42-F41) -> n/a | G44: =IF(OR(ISBLANK(G9),ISBLANK(G16),ISBLANK(G35)),"n/a",G42-G41) -> n/a | H44: =IF(OR(ISBLANK(H9),ISBLANK(H16),ISBLANK(H35)),"n/a",H42-H41) -> n/a | I44: =IF(OR(ISBLANK(I9),ISBLANK(I16),ISBLANK(I35)),"n/a",I42-I41) -> n/a | ... M44: =IF(OR(ISBLANK(M9),ISBLANK(M16),ISBLANK(M35)),"n/a",M42-M41) -> n/a | N44: =IF(COUNT($B$9:$M$9)=0,"n/a",N42-SUMIF($B$9:$M$9,"<>",B41:M41)) -> n/a
A45: Variance (%) | B45: =IF(OR(ISBLANK(B9),ISBLANK(B16),ISBLANK(B35)),"n/a",IF(B41=0,"n/a",(B42-B41)/B41)) -> n/a | C45: =IF(OR(ISBLANK(C9),ISBLANK(C16),ISBLANK(C35)),"n/a",IF(C41=0,"n/a",(C42-C41)/C41)) -> n/a | D45: =IF(OR(ISBLANK(D9),ISBLANK(D16),ISBLANK(D35)),"n/a",IF(D41=0,"n/a",(D42-D41)/D41)) -> n/a | E45: =IF(OR(ISBLANK(E9),ISBLANK(E16),ISBLANK(E35)),"n/a",IF(E41=0,"n/a",(E42-E41)/E41)) -> n/a | F45: =IF(OR(ISBLANK(F9),ISBLANK(F16),ISBLANK(F35)),"n/a",IF(F41=0,"n/a",(F42-F41)/F41)) -> n/a | G45: =IF(OR(ISBLANK(G9),ISBLANK(G16),ISBLANK(G35)),"n/a",IF(G41=0,"n/a",(G42-G41)/G41)) -> n/a | H45: =IF(OR(ISBLANK(H9),ISBLANK(H16),ISBLANK(H35)),"n/a",IF(H41=0,"n/a",(H42-H41)/H41)) -> n/a | I45: =IF(OR(ISBLANK(I9),ISBLANK(I16),ISBLANK(I35)),"n/a",IF(I41=0,"n/a",(I42-I41)/I41)) -> n/a | ... M45: =IF(OR(ISBLANK(M9),ISBLANK(M16),ISBLANK(M35)),"n/a",IF(M41=0,"n/a",(M42-M41)/M41)) -> n/a | N45: =IF(N44="n/a","n/a",N44/SUMIF($B$9:$M$9,"<>",B41:M41)) -> n/a
A47: EBITDA Margin %
A48: Budget % | B48: =IF(B8=0,"n/a",B41/B8) -> 0.2 | C48: =IF(C8=0,"n/a",C41/C8) -> 0.2 | D48: =IF(D8=0,"n/a",D41/D8) -> 0.2 | E48: =IF(E8=0,"n/a",E41/E8) -> 0.2 | F48: =IF(F8=0,"n/a",F41/F8) -> 0.2 | G48: =IF(G8=0,"n/a",G41/G8) -> 0.2 | H48: =IF(H8=0,"n/a",H41/H8) -> 0.2 | I48: =IF(I8=0,"n/a",I41/I8) -> 0.2 | ... N48: =IF(N8=0,"n/a",N41/N8) -> 0.2
A49: Actual % | B49: =IF(OR(ISBLANK(B9),ISBLANK(B16),ISBLANK(B35)),"n/a",IF(B9=0,"n/a",B42/B9)) -> n/a | C49: =IF(OR(ISBLANK(C9),ISBLANK(C16),ISBLANK(C35)),"n/a",IF(C9=0,"n/a",C42/C9)) -> n/a | D49: =IF(OR(ISBLANK(D9),ISBLANK(D16),ISBLANK(D35)),"n/a",IF(D9=0,"n/a",D42/D9)) -> n/a | E49: =IF(OR(ISBLANK(E9),ISBLANK(E16),ISBLANK(E35)),"n/a",IF(E9=0,"n/a",E42/E9)) -> n/a | F49: =IF(OR(ISBLANK(F9),ISBLANK(F16),ISBLANK(F35)),"n/a",IF(F9=0,"n/a",F42/F9)) -> n/a | G49: =IF(OR(ISBLANK(G9),ISBLANK(G16),ISBLANK(G35)),"n/a",IF(G9=0,"n/a",G42/G9)) -> n/a | H49: =IF(OR(ISBLANK(H9),ISBLANK(H16),ISBLANK(H35)),"n/a",IF(H9=0,"n/a",H42/H9)) -> n/a | I49: =IF(OR(ISBLANK(I9),ISBLANK(I16),ISBLANK(I35)),"n/a",IF(I9=0,"n/a",I42/I9)) -> n/a | ... M49: =IF(OR(ISBLANK(M9),ISBLANK(M16),ISBLANK(M35)),"n/a",IF(M9=0,"n/a",M42/M9)) -> n/a | N49: =IF(COUNT($B$9:$M$9)=0,"n/a",IF(N9=0,"n/a",N42/N9)) -> n/a
A50: Variance (pp) | B50: =IF(B49="n/a","n/a",B49-B48) -> n/a | C50: =IF(C49="n/a","n/a",C49-C48) -> n/a | D50: =IF(D49="n/a","n/a",D49-D48) -> n/a | E50: =IF(E49="n/a","n/a",E49-E48) -> n/a | F50: =IF(F49="n/a","n/a",F49-F48) -> n/a | G50: =IF(G49="n/a","n/a",G49-G48) -> n/a | H50: =IF(H49="n/a","n/a",H49-H48) -> n/a | I50: =IF(I49="n/a","n/a",I49-I48) -> n/a | ... N50: =IF(N49="n/a","n/a",N49-N48) -> n/a
A52: Net Income
A53: Budget | B53: ='Monthly Forecast'!B18 -> 960 | C53: ='Monthly Forecast'!C18 -> 960 | D53: ='Monthly Forecast'!D18 -> 960 | E53: ='Monthly Forecast'!E18 -> 960 | F53: ='Monthly Forecast'!F18 -> 960 | G53: ='Monthly Forecast'!G18 -> 960 | H53: ='Monthly Forecast'!H18 -> 960 | I53: ='Monthly Forecast'!I18 -> 960 | ... M53: ='Monthly Forecast'!M18 -> 960 | N53: =SUM(B53:M53) -> 11520
A54: Actual (derived) | B54: =IF(OR(ISBLANK(B9),ISBLANK(B16),ISBLANK(B35)),"",(B42-'Monthly Forecast'!B13-'Monthly Forecast'!B15)*(1-Assumptions!$C$11)) | C54: =IF(OR(ISBLANK(C9),ISBLANK(C16),ISBLANK(C35)),"",(C42-'Monthly Forecast'!C13-'Monthly Forecast'!C15)*(1-Assumptions!$C$11)) | D54: =IF(OR(ISBLANK(D9),ISBLANK(D16),ISBLANK(D35)),"",(D42-'Monthly Forecast'!D13-'Monthly Forecast'!D15)*(1-Assumptions!$C$11)) | E54: =IF(OR(ISBLANK(E9),ISBLANK(E16),ISBLANK(E35)),"",(E42-'Monthly Forecast'!E13-'Monthly Forecast'!E15)*(1-Assumptions!$C$11)) | F54: =IF(OR(ISBLANK(F9),ISBLANK(F16),ISBLANK(F35)),"",(F42-'Monthly Forecast'!F13-'Monthly Forecast'!F15)*(1-Assumptions!$C$11)) | G54: =IF(OR(ISBLANK(G9),ISBLANK(G16),ISBLANK(G35)),"",(G42-'Monthly Forecast'!G13-'Monthly Forecast'!G15)*(1-Assumptions!$C$11)) | H54: =IF(OR(ISBLANK(H9),ISBLANK(H16),ISBLANK(H35)),"",(H42-'Monthly Forecast'!H13-'Monthly Forecast'!H15)*(1-Assumptions!$C$11)) | I54: =IF(OR(ISBLANK(I9),ISBLANK(I16),ISBLANK(I35)),"",(I42-'Monthly Forecast'!I13-'Monthly Forecast'!I15)*(1-Assumptions!$C$11)) | ... M54: =IF(OR(ISBLANK(M9),ISBLANK(M16),ISBLANK(M35)),"",(M42-'Monthly Forecast'!M13-'Monthly Forecast'!M15)*(1-Assumptions!$C$11)) | N54: =IF(COUNT($B$9:$M$9)=0,"",SUM(B54:M54))
A55: Latest Estimate | B55: =IF(OR(ISBLANK(B9),ISBLANK(B16),ISBLANK(B35)),B53,B54) -> 960 | C55: =IF(OR(ISBLANK(C9),ISBLANK(C16),ISBLANK(C35)),C53,C54) -> 960 | D55: =IF(OR(ISBLANK(D9),ISBLANK(D16),ISBLANK(D35)),D53,D54) -> 960 | E55: =IF(OR(ISBLANK(E9),ISBLANK(E16),ISBLANK(E35)),E53,E54) -> 960 | F55: =IF(OR(ISBLANK(F9),ISBLANK(F16),ISBLANK(F35)),F53,F54) -> 960 | G55: =IF(OR(ISBLANK(G9),ISBLANK(G16),ISBLANK(G35)),G53,G54) -> 960 | H55: =IF(OR(ISBLANK(H9),ISBLANK(H16),ISBLANK(H35)),H53,H54) -> 960 | I55: =IF(OR(ISBLANK(I9),ISBLANK(I16),ISBLANK(I35)),I53,I54) -> 960 | ... M55: =IF(OR(ISBLANK(M9),ISBLANK(M16),ISBLANK(M35)),M53,M54) -> 960 | N55: =SUM(B55:M55) -> 11520
A56: Variance ($) | B56: =IF(OR(ISBLANK(B9),ISBLANK(B16),ISBLANK(B35)),"n/a",B54-B53) -> n/a | C56: =IF(OR(ISBLANK(C9),ISBLANK(C16),ISBLANK(C35)),"n/a",C54-C53) -> n/a | D56: =IF(OR(ISBLANK(D9),ISBLANK(D16),ISBLANK(D35)),"n/a",D54-D53) -> n/a | E56: =IF(OR(ISBLANK(E9),ISBLANK(E16),ISBLANK(E35)),"n/a",E54-E53) -> n/a | F56: =IF(OR(ISBLANK(F9),ISBLANK(F16),ISBLANK(F35)),"n/a",F54-F53) -> n/a | G56: =IF(OR(ISBLANK(G9),ISBLANK(G16),ISBLANK(G35)),"n/a",G54-G53) -> n/a | H56: =IF(OR(ISBLANK(H9),ISBLANK(H16),ISBLANK(H35)),"n/a",H54-H53) -> n/a | I56: =IF(OR(ISBLANK(I9),ISBLANK(I16),ISBLANK(I35)),"n/a",I54-I53) -> n/a | ... M56: =IF(OR(ISBLANK(M9),ISBLANK(M16),ISBLANK(M35)),"n/a",M54-M53) -> n/a | N56: =IF(COUNT($B$9:$M$9)=0,"n/a",N54-SUMIF($B$9:$M$9,"<>",B53:M53)) -> n/a
A57: Variance (%) | B57: =IF(OR(ISBLANK(B9),ISBLANK(B16),ISBLANK(B35)),"n/a",IF(B53=0,"n/a",(B54-B53)/B53)) -> n/a | C57: =IF(OR(ISBLANK(C9),ISBLANK(C16),ISBLANK(C35)),"n/a",IF(C53=0,"n/a",(C54-C53)/C53)) -> n/a | D57: =IF(OR(ISBLANK(D9),ISBLANK(D16),ISBLANK(D35)),"n/a",IF(D53=0,"n/a",(D54-D53)/D53)) -> n/a | E57: =IF(OR(ISBLANK(E9),ISBLANK(E16),ISBLANK(E35)),"n/a",IF(E53=0,"n/a",(E54-E53)/E53)) -> n/a | F57: =IF(OR(ISBLANK(F9),ISBLANK(F16),ISBLANK(F35)),"n/a",IF(F53=0,"n/a",(F54-F53)/F53)) -> n/a | G57: =IF(OR(ISBLANK(G9),ISBLANK(G16),ISBLANK(G35)),"n/a",IF(G53=0,"n/a",(G54-G53)/G53)) -> n/a | H57: =IF(OR(ISBLANK(H9),ISBLANK(H16),ISBLANK(H35)),"n/a",IF(H53=0,"n/a",(H54-H53)/H53)) -> n/a | I57: =IF(OR(ISBLANK(I9),ISBLANK(I16),ISBLANK(I35)),"n/a",IF(I53=0,"n/a",(I54-I53)/I53)) -> n/a | ... M57: =IF(OR(ISBLANK(M9),ISBLANK(M16),ISBLANK(M35)),"n/a",IF(M53=0,"n/a",(M54-M53)/M53)) -> n/a | N57: =IF(N56="n/a","n/a",N56/SUMIF($B$9:$M$9,"<>",B53:M53)) -> n/a
A59: Net Margin %
A60: Budget % | B60: =IF(B8=0,"n/a",B53/B8) -> 0.10666667 | C60: =IF(C8=0,"n/a",C53/C8) -> 0.10666667 | D60: =IF(D8=0,"n/a",D53/D8) -> 0.10666667 | E60: =IF(E8=0,"n/a",E53/E8) -> 0.10666667 | F60: =IF(F8=0,"n/a",F53/F8) -> 0.10666667 | G60: =IF(G8=0,"n/a",G53/G8) -> 0.10666667 | H60: =IF(H8=0,"n/a",H53/H8) -> 0.10666667 | I60: =IF(I8=0,"n/a",I53/I8) -> 0.10666667 | ... N60: =IF(N8=0,"n/a",N53/N8) -> 0.10666667
A61: Actual % | B61: =IF(OR(ISBLANK(B9),ISBLANK(B16),ISBLANK(B35)),"n/a",IF(B9=0,"n/a",B54/B9)) -> n/a | C61: =IF(OR(ISBLANK(C9),ISBLANK(C16),ISBLANK(C35)),"n/a",IF(C9=0,"n/a",C54/C9)) -> n/a | D61: =IF(OR(ISBLANK(D9),ISBLANK(D16),ISBLANK(D35)),"n/a",IF(D9=0,"n/a",D54/D9)) -> n/a | E61: =IF(OR(ISBLANK(E9),ISBLANK(E16),ISBLANK(E35)),"n/a",IF(E9=0,"n/a",E54/E9)) -> n/a | F61: =IF(OR(ISBLANK(F9),ISBLANK(F16),ISBLANK(F35)),"n/a",IF(F9=0,"n/a",F54/F9)) -> n/a | G61: =IF(OR(ISBLANK(G9),ISBLANK(G16),ISBLANK(G35)),"n/a",IF(G9=0,"n/a",G54/G9)) -> n/a | H61: =IF(OR(ISBLANK(H9),ISBLANK(H16),ISBLANK(H35)),"n/a",IF(H9=0,"n/a",H54/H9)) -> n/a | I61: =IF(OR(ISBLANK(I9),ISBLANK(I16),ISBLANK(I35)),"n/a",IF(I9=0,"n/a",I54/I9)) -> n/a | ... M61: =IF(OR(ISBLANK(M9),ISBLANK(M16),ISBLANK(M35)),"n/a",IF(M9=0,"n/a",M54/M9)) -> n/a | N61: =IF(COUNT($B$9:$M$9)=0,"n/a",IF(N9=0,"n/a",N54/N9)) -> n/a
A62: Variance (pp) | B62: =IF(B61="n/a","n/a",B61-B60) -> n/a | C62: =IF(C61="n/a","n/a",C61-C60) -> n/a | D62: =IF(D61="n/a","n/a",D61-D60) -> n/a | E62: =IF(E61="n/a","n/a",E61-E60) -> n/a | F62: =IF(F61="n/a","n/a",F61-F60) -> n/a | G62: =IF(G61="n/a","n/a",G61-G60) -> n/a | H62: =IF(H61="n/a","n/a",H61-H60) -> n/a | I62: =IF(I61="n/a","n/a",I61-I60) -> n/a | ... N62: =IF(N61="n/a","n/a",N61-N60) -> n/a
A64: Note: months are assumed to "close" together — i.e. once you enter a month's Revenue, also enter that month's COGS and Opex, since Gross Profit / EBITDA / Net Income for that month need all three to compute. Net Income (Actual) keeps Depreciation, Interest, and Tax rate at Budget levels, since this tab does not separately track those as actuals — so it isolates the effect of Revenue/COGS/Opex variance specifically, which is normally what "why is profit off budget" questions are about.

Sheet Insights & Recommendations
A1: Insights & Recommendations
A2: ="Active scenario: "&Assumptions!$B$4&" — figures below update automatically if you change it." -> Active scenario: Base — figures below update automatically if you change it.
A4: Key Findings
A5: ="1. Revenue is projected to grow from "&TEXT('Income Statement'!B4,"$#,##0")&" in 2026A to "&TEXT('Income Statement'!G4,"$#,##0")&" by 2031E ("&TEXT(('Income Statement'!G4/'Income Statement'!B4)^(1/5)-1,"0.0%")&" CAGR)." -> 1. Revenue is projected to grow from $100,000 in 2026A to $146,933 by 2031E (8.0% CAGR).
A6: ="2. Net Income grows faster than revenue ("&TEXT(('Income Statement'!G14/'Income Statement'!B14)^(1/5)-1,"0.0%")&" CAGR vs "&TEXT(('Income Statement'!G4/'Income Statement'!B4)^(1/5)-1,"0.0%")&"), because interest expense stays flat on constant debt while revenue grows." -> 2. Net Income grows faster than revenue (8.9% CAGR vs 8.0%), because interest expense stays flat on constant debt while revenue grows.
A7: ="3. Debt/Equity falls from "&TEXT('Ratios & KPIs'!B10,"0.0")&"x in 2026A to "&TEXT('Ratios & KPIs'!G10,"0.0")&"x by 2031E, so the business becomes steadily less dependent on debt as retained earnings build up equity." -> 3. Debt/Equity falls from 0.9x in 2026A to 0.3x by 2031E, so the business becomes steadily less dependent on debt as retained earnings build up equity.
A8: ="4. Current Ratio improves from "&TEXT('Ratios & KPIs'!B9,"0.0")&"x to "&TEXT('Ratios & KPIs'!G9,"0.0")&"x, driven mainly by cash accumulating on the balance sheet rather than by a change in the underlying working-capital assumptions." -> 4. Current Ratio improves from 4.7x to 9.8x, driven mainly by cash accumulating on the balance sheet rather than by a change in the underlying working-capital assumptions.
A9: ="5. The Downside scenario cuts 2031E Net Income to "&TEXT('Executive Summary'!D37,"$#,##0")&" (vs "&TEXT('Executive Summary'!B37,"$#,##0")&" in Base) — a small drop in margin assumptions has an outsized effect on the bottom line." -> 5. The Downside scenario cuts 2031E Net Income to $3,860 (vs $16,192 in Base) — a small drop in margin assumptions has an outsized effect on the bottom line.
A11: Recommendations
A12: 1. Track monthly Actuals against the Budget from month one (see the Actual vs Budget vs Forecast tab) — catching a variance early is far cheaper than discovering it at year-end.
A13: 2. Since profitability is highly sensitive to COGS% and Opex% (see how much the Downside scenario compresses Net Income), prioritize renegotiating supplier terms or tightening cost control over simply chasing more revenue.
A14: ="3. The growing cash balance ("&TEXT('Balance Sheet'!B4,"$#,##0")&" -> "&TEXT('Balance Sheet'!G4,"$#,##0")&") is a good problem to have — consider whether some of it should fund debt paydown, a dividend, or reinvestment, rather than sitting idle." -> 3. The growing cash balance ($15,000 -> $71,268) is a good problem to have — consider whether some of it should fund debt paydown, a dividend, or reinvestment, rather than sitting idle.
A15: 4. Revisit the working-capital assumptions (AR/Inventory/AP days) against real collections and supplier data once available — these currently drive the Balance Sheet but are estimates, not measured figures.
A16: 5. Re-run this model under the Upside and Downside scenarios before making major commitments (hiring, capex, financing) so decisions are stress-tested against more than the single most-likely case.
A18: Note: findings above are generated live from the model's formulas (they will update if you change assumptions or the scenario). Recommendations are qualitative judgment calls a preparer would normally validate with management before presenting.
